README.txt
setup.cfg
setup.py
collective/__init__.py
collective.progressbar.egg-info/PKG-INFO
collective.progressbar.egg-info/SOURCES.txt
collective.progressbar.egg-info/dependency_links.txt
collective.progressbar.egg-info/entry_points.txt
collective.progressbar.egg-info/namespace_packages.txt
collective.progressbar.egg-info/not-zip-safe
collective.progressbar.egg-info/requires.txt
collective.progressbar.egg-info/top_level.txt
collective/progressbar/README.txt
collective/progressbar/__init__.py
collective/progressbar/configure.zcml
collective/progressbar/events.py
collective/progressbar/iframe.pt
collective/progressbar/interfaces.py
collective/progressbar/progressbar.pt
collective/progressbar/demo/__init__.py
collective/progressbar/demo/configure.zcml
collective/progressbar/demo/demo.py
docs/HISTORY.txt