Metadata-Version: 1.0
Name: collective.progressbar
Version: 0.5
Summary: HTML and Javascript progress bar for Plone
Home-page: http://svn.plone.org/svn/collective/collective.progressbar
Author: Upfront Systems
Author-email: info@upfrontsystems.co.za
License: GPL
Keywords: plone progress bar
Platform: UNKNOWN
Classifier: Programming Language :: Python
Classifier: Topic :: Software Development :: Libraries :: Python Modules
